ttsprototyper/__init__.py
ttsprototyper/main.py
ttsprototyper/ontology.py
ttsprototyper-0.4.0.dist-info/LICENSE
ttsprototyper-0.4.0.dist-info/METADATA
ttsprototyper-0.4.0.dist-info/WHEEL
ttsprototyper-0.4.0.dist-info/RECORD
