Metadata-Version: 2.3
Name: ttsprototyper
Version: 0.4.0
Summary: Technical Trading Strategy Prototyper - Visual backtesting framework for developing and analyzing trading strategies with comprehensive charting and performance analysis
License: GNU GPL v3.0
Author: Nils P. Kujath
Author-email: 63961429+NilsKujath@users.noreply.github.com
Requires-Python: >=3.11
Classifier: License :: OSI Approved :: GNU General Public License v3 (GPLv3)
Classifier: Programming Language :: Python :: 3.11
Classifier: Development Status :: 2 - Pre-Alpha
Classifier: Operating System :: OS Independent
Classifier: Intended Audience :: Developers
Requires-Dist: matplotlib (>=3.7.0,<4.0.0)
Requires-Dist: pandas (>=2.3.0,<3.0.0)
Requires-Dist: rich (>=14.0.0,<15.0.0)
